tests/__init__.py
tests/it_ds_mem_profiling.py
tests/test_it_ds.py
tests/test_it_ds_pl.py
tests/test_it_ds_pl.slurm
tests/test_virtual_map.py
tests/utils.py
zarrdataset/__init__.py
zarrdataset/iterable_dataset.py
zarrdataset/virtual_map.py
zarr_torch_dataset-0.0.4.dist-info/METADATA
zarr_torch_dataset-0.0.4.dist-info/WHEEL
zarr_torch_dataset-0.0.4.dist-info/licenses/LICENSE.txt
zarr_torch_dataset-0.0.4.dist-info/RECORD
