Metadata-Version: 2.3
Name: zarr-torch-dataset
Version: 0.0.4
Summary: Pytorch dataset with Zarr backend
Project-URL: Repository, https://gitlab.in2p3.fr/ipsl/espri/espri-ia/projects/zarr-torch-dataset
Author-email: Sébastien Gardoll <sebastien.gardoll@cnrs.fr>
License: CECILL-2.1
Requires-Python: >=3.11
Requires-Dist: numpy>=2.1.3
Requires-Dist: torch>=2.6
Requires-Dist: zarr>=3.0.8
